djangocms_text/__init__.py
djangocms_text/apps.py
djangocms_text/cms_plugins.py
djangocms_text/cms_toolbars.py
djangocms_text/editors.py
djangocms_text/fields.py
djangocms_text/forms.py
djangocms_text/html.py
djangocms_text/models.py
djangocms_text/settings.py
djangocms_text/utils.py
djangocms_text/widgets.py
djangocms_text/contrib/__init__.py
djangocms_text/contrib/text_ckeditor4/__init__.py
djangocms_text/contrib/text_ckeditor4/static/djangocms_text/bundles/bundle.ckeditor4.min.js
djangocms_text/contrib/text_ckeditor4/static/djangocms_text/bundles/bundle.ckeditor4.min.js.map
djangocms_text/contrib/text_ckeditor4/static/djangocms_text/css/cms.ckeditor4.css
djangocms_text/contrib/text_ckeditor4/static/djangocms_text/icons/cmsplugins.svg
djangocms_text/contrib/text_ckeditor4/static/djangocms_text/js/basepath.js
djangocms_text/contrib/text_ckeditor4/static/djangocms_text/vendor/ckeditor4/CHANGES.md
djangocms_text/contrib/text_ckeditor4/static/djangocms_text/vendor/ckeditor4/LICENSE.md
djangocms_text/contrib/text_ckeditor4/static/djangocms_text/vendor/ckeditor4/README.md
djangocms_text/contrib/text_ckeditor4/static/djangocms_text/vendor/ckeditor4/SECURITY.md
djangocms_text/contrib/text_ckeditor4/static/djangocms_text/vendor/ckeditor4/bender-runner.config.json
djangocms_text/contrib/text_ckeditor4/static/djangocms_text/vendor/ckeditor4/build-config.js
djangocms_text/contrib/text_ckeditor4/static/djangocms_text/vendor/ckeditor4/ckeditor.js
djangocms_text/contrib/text_ckeditor4/static/djangocms_text/vendor/ckeditor4/config.js
djangocms_text/contrib/text_ckeditor4/static/djangocms_text/vendor/ckeditor4/contents.css
djangocms_text/contrib/text_ckeditor4/static/djangocms_text/vendor/ckeditor4/styles.js
djangocms_text/contrib/text_ckeditor4/static/djangocms_text/vendor/ckeditor4/adapters/jquery.js
djangocms_text/contrib/text_ckeditor4/static/djangocms_text/vendor/ckeditor4/lang/af.js
djangocms_text/contrib/text_ckeditor4/static/djangocms_text/vendor/ckeditor4/lang/ar.js
djangocms_text-0.9.3.dist-info/METADATA
djangocms_text-0.9.3.dist-info/WHEEL
djangocms_text-0.9.3.dist-info/licenses/LICENSE
djangocms_text-0.9.3.dist-info/RECORD
